oatmeal/__init__.py
oatmeal/device.py
oatmeal/protocol.py
oatmeal-1.1.dist-info/LICENSE
oatmeal-1.1.dist-info/METADATA
oatmeal-1.1.dist-info/WHEEL
oatmeal-1.1.dist-info/top_level.txt
oatmeal-1.1.dist-info/RECORD
