Metadata-Version: 2.1
Name: oatmeal
Version: 1.1
Summary: A protocol to control and communicate with Arduino devices from Python.
Home-page: https://github.com/shielddx/oatmeal-protocol
Author: Shield Dx and Oatmeal Protocol Authors
Author-email: turner.isaac@gmail.com
License: UNKNOWN
Platform: UNKNOWN
Classifier: Programming Language :: Python :: 3
Classifier: License :: OSI Approved :: Apache Software License
Classifier: Operating System :: OS Independent
Classifier: Topic :: Software Development :: Embedded Systems
Classifier: Topic :: Software Development :: Object Brokering
Classifier: Topic :: Terminals :: Serial
Requires-Dist: pyserial
